Workbook

Sheet Raw_Data

Sheet DCF
A1: Metric | B1: 2022A | C1: 2023A | D1: 2024A | E1: 2025A | F1: 2026E | G1: 2027E | H1: 2028E | I1: 2029E | J1: 2030E | L1: Input | M1: Value | R1: Metric | S1: Value | U1: All figures in USD Millions
A2: Revenue | B2: 26974 | C2: 60922 | D2: 130497 | E2: 215938 | F2: =E2*(1+F3) -> 269922.5 | G2: =F2*(1+G3) -> 323907 | H2: =G2*(1+H3) -> 372493.05 | I2: =H2*(1+I3) -> 409742.36 | J2: =I2*(1+J3) -> 442521.74 | L2: WACC | M2: =Scenarios!G13 -> 0.12 | R2: PV Forecast FCF | S2: =SUM(P8:P12) -> 628803.62
A3: Growth % | B3: - | C3: 1.259 | D3: 1.142 | E3: 0.655 | F3: =Scenarios!G3 -> 0.25 | G3: =Scenarios!G4 -> 0.2 | H3: =Scenarios!G5 -> 0.15 | I3: =Scenarios!G6 -> 0.1 | J3: =Scenarios!G7 -> 0.08 | L3: Terminal Growth | M3: =Scenarios!G14 -> 0.02 | R3: PV Terminal Value | S3: =P17 -> 1219134.5
A4: EBITDA | B4: 5986 | C4: 35583 | D4: 86137 | E4: 144552 | F4: =F2*F5 -> 161953.5 | G4: =G2*G5 -> 191105.13 | H4: =H2*H5 -> 216045.97 | I4: =I2*I5 -> 233553.14 | J4: =J2*J5 -> 247812.18 | R4: Enterprise Value | S4: =P18 -> 1847938.1
A5: EBITDA Margin | B5: =B4/B2 -> 0.2219174 | C5: =C4/C2 -> 0.58407472 | D5: =D4/D2 -> 0.66006881 | E5: =E4/E2 -> 0.66941437 | F5: =Scenarios!G8 -> 0.6 | G5: =Scenarios!G9 -> 0.59 | H5: =Scenarios!G10 -> 0.58 | I5: =Scenarios!G11 -> 0.57 | J5: =Scenarios!G12 -> 0.56
A6: Tax Rate | B6: - | C6: - | D6: - | E6: - | F6: =Assumptions!B6 -> 0.15 | G6: =Assumptions!B6 -> 0.15 | H6: =Assumptions!B6 -> 0.15 | I6: =Assumptions!B6 -> 0.15 | J6: =Assumptions!B6 -> 0.15
A7: FCF | B7: - | C7: - | D7: - | E7: - | F7: =F4*(1-F6) -> 137660.48 | G7: =G4*(1-G6) -> 162439.36 | H7: =H4*(1-H6) -> 183639.07 | I7: =I4*(1-I6) -> 198520.17 | J7: =J4*(1-J6) -> 210640.35 | L7: Year | M7: Discount Factor | O7: Year | P7: PV FCF
L8: 2026 | M8: =1/(1+$M$2)^1 -> 0.89285714 | O8: 2026 | P8: =F7*M8 -> 122911.14
L9: 2027 | M9: =1/(1+$M$2)^2 -> 0.79719388 | O9: 2027 | P9: =G7*M9 -> 129495.66
L10: 2028 | M10: =1/(1+$M$2)^3 -> 0.71178025 | O10: 2028 | P10: =H7*M10 -> 130710.67
L11: 2029 | M11: =1/(1+$M$2)^4 -> 0.63551808 | O11: 2029 | P11: =I7*M11 -> 126163.16
L12: 2030 | M12: =1/(1+$M$2)^5 -> 0.56742686 | O12: 2030 | P12: =J7*M12 -> 119522.99
O15: Terminal FCF | P15: =J7*(1+$M$3) -> 214853.16
O16: Terminal Value | P16: =P15/($M$2-$M$3) -> 2148531.6
O17: PV Terminal Value | P17: =P16*M12 -> 1219134.5
O18: Enterprise Value | P18: =SUM(P8:P12)+P17 -> 1847938.1

Sheet Scenarios
A1: Assumption | B1: Bear | C1: Base | D1: Bull
A2: Revenue Growth 2026 | B2: 0.25 | C2: 0.347 | D2: 0.45 | F2: Active Scenario | G2: Bear
A3: Revenue Growth 2027 | B3: 0.2 | C3: 0.347 | D3: 0.4 | F3: Growth 2026 | G3: =INDEX(B2:D2,1,MATCH($G$2,$B$1:$D$1,0)) -> 0.25
A4: Revenue Growth 2028 | B4: 0.15 | C4: 0.25 | D4: 0.35 | F4: Growth 2027 | G4: =INDEX(B3:D3,1,MATCH($G$2,$B$1:$D$1,0)) -> 0.2
A5: Revenue Growth 2029 | B5: 0.1 | C5: 0.18 | D5: 0.25 | F5: Growth 2028 | G5: =INDEX(B4:D4,1,MATCH($G$2,$B$1:$D$1,0)) -> 0.15
A6: Revenue Growth 2030 | B6: 0.08 | C6: 0.12 | D6: 0.18 | F6: Growth 2029 | G6: =INDEX(B5:D5,1,MATCH($G$2,$B$1:$D$1,0)) -> 0.1
A7: EBITDA Margin 2026 | B7: 0.6 | C7: 0.66 | D7: 0.7 | F7: Growth 2030 | G7: =INDEX(B6:D6,1,MATCH($G$2,$B$1:$D$1,0)) -> 0.08
A8: EBITDA Margin 2027 | B8: 0.59 | C8: 0.66 | D8: 0.69 | F8: EBITDA Margin 2026 | G8: =INDEX(B7:D7,1,MATCH($G$2,$B$1:$D$1,0)) -> 0.6
A9: EBITDA Margin 2028 | B9: 0.58 | C9: 0.65 | D9: 0.68 | F9: EBITDA Margin 2027 | G9: =INDEX(B8:D8,1,MATCH($G$2,$B$1:$D$1,0)) -> 0.59
A10: EBITDA Margin 2029 | B10: 0.57 | C10: 0.64 | D10: 0.67 | F10: EBITDA Margin 2028 | G10: =INDEX(B9:D9,1,MATCH($G$2,$B$1:$D$1,0)) -> 0.58
A11: EBITDA Margin 2030 | B11: 0.56 | C11: 0.63 | D11: 0.66 | F11: EBITDA Margin 2029 | G11: =INDEX(B10:D10,1,MATCH($G$2,$B$1:$D$1,0)) -> 0.57
A12: WACC | B12: 0.12 | C12: 0.1 | D12: 0.08 | F12: EBITDA Margin 2030 | G12: =INDEX(B11:D11,1,MATCH($G$2,$B$1:$D$1,0)) -> 0.56
A13: Terminal Growth | B13: 0.02 | C13: 0.03 | D13: 0.04 | F13: WACC | G13: =INDEX(B12:D12,1,MATCH($G$2,$B$1:$D$1,0)) -> 0.12
F14: Terminal Growth | G14: =INDEX(B13:D13,1,MATCH($G$2,$B$1:$D$1,0)) -> 0.02

Sheet Dashboard

Sheet Pivot_Analysis

Sheet Assumptions
A1: Assumption | B1: Value | C1: Source
A2: FY2027 Revenue | B2: 391.66B | C2: Analyst Consensus Estimates
A3: FY2027 EPS | B3: 8.96 | C3: Analyst Consensus Estimates
A4: WACC | B4: 0.1 | C4: Based on valuation practice and benchmarked against semiconductor industry estimates published by Aswath Damodaran
A5: Terminal Growth | B5: 0.03 | C5: Long-term GDP growth proxy commonly used in DCF models
A6: Tax Rate | B6: 0.15 | C6: Approximation based on Nvidia's recent effective tax rate and forecast assumption
A7: FY2026 Growth | B7: 0.347 | C7: Implied growth from FY2025 Revenue to FY2027 Analyst Consensus Revenue
A8: FY2027 Growth | B8: 0.347 | C8: Implied growth from FY2025 Revenue to FY2027 Analyst Consensus Revenue
A9: FY2028 Growth | B9: 0.25 | C9: Growth normalization assumption
A10: FY2029 Growth | B10: 0.18 | C10: Growth normalization assumption
A11: FY2030 Growth | B11: 0.12 | C11: Growth normalization assumption

Sheet Model_Notes
